protorpc/__init__.py
protorpc/definition.py
protorpc/definition_test.py
protorpc/descriptor.py
protorpc/descriptor_test.py
protorpc/end2end_test.py
protorpc/generate.py
protorpc/generate_proto.py
protorpc/generate_proto_test.py
protorpc/generate_python.py
protorpc/generate_python_test.py
protorpc/generate_test.py
protorpc/google_imports.py
protorpc/message_types.py
protorpc/message_types_test.py
protorpc/messages.py
protorpc/messages_test.py
protorpc/non_sdk_imports.py
protorpc/protobuf.py
protorpc/protobuf_test.py
protorpc/protojson.py
protorpc/protojson_test.py
protorpc/protorpc_test_pb2.py
protorpc/protourlencode.py
protorpc/protourlencode_test.py
protorpc/registry.py
protorpc/registry_test.py
protorpc/remote.py
protorpc/remote_test.py
protorpc/test_util.py
protorpc/transport.py
protorpc/transport_test.py
protorpc/util.py
protorpc/util_test.py
protorpc/webapp_test_util.py
protorpc-0.11.0.dist-info/DESCRIPTION.rst
protorpc-0.11.0.dist-info/entry_points.txt
protorpc-0.11.0.dist-info/METADATA
protorpc-0.11.0.dist-info/metadata.json
protorpc-0.11.0.dist-info/RECORD
protorpc-0.11.0.dist-info/top_level.txt
protorpc-0.11.0.dist-info/WHEEL
